[
  {
    "appid": 365420,
    "title": "Apollo4x",
    "premium": false,
    "cover_url": "NO CONTENT",
    "publishers": [],
    "genres": [],
    "specification": {
      "minimum": "",
      "recommended": ""
    }
  },
  {
    "appid": 365430,
    "title": "Everything is Black and White",
    "premium": false,
    "cover_url": "NO CONTENT",
    "publishers": [],
    "genres": [],
    "specification": {
      "minimum": "",
      "recommended": ""
    }
  },
  {
    "appid": 365450,
    "title": "Hacknet",
    "premium": false,
    "cover_url": "https://shared.steamstatic.com/store_item_assets/steam/apps/365450/library_600x900.jpg?t=1755052386",
    "publishers": [],
    "genres": [],
    "specification": {
      "minimum": "",
      "recommended": ""
    }
  },
  {
    "appid": 365460,
    "title": "CHARIOT WARS",
    "premium": false,
    "cover_url": "NO CONTENT",
    "publishers": [],
    "genres": [],
    "specification": {
      "minimum": "",
      "recommended": ""
    }
  },
  {
    "appid": 365480,
    "title": "Ravenmark: Scourge of Estellion",
    "premium": true,
    "cover_url": "https://shared.steamstatic.com/store_item_assets/steam/apps/365480/library_600x900.jpg?t=1575024835",
    "publishers": [],
    "genres": [],
    "specification": {
      "minimum": "",
      "recommended": ""
    }
  },
  {
    "appid": 365500,
    "title": "quadrant",
    "premium": false,
    "cover_url": "NO CONTENT",
    "publishers": [],
    "genres": [],
    "specification": {
      "minimum": "",
      "recommended": ""
    }
  },
  {
    "appid": 365510,
    "title": "Flip",
    "premium": false,
    "cover_url": "NO CONTENT",
    "publishers": [],
    "genres": [],
    "specification": {
      "minimum": "",
      "recommended": ""
    }
  },
  {
    "appid": 365560,
    "title": "Battle of the Bulge",
    "premium": false,
    "cover_url": "https://shared.steamstatic.com/store_item_assets/steam/apps/365560/library_600x900.jpg?t=1564045165",
    "publishers": [],
    "genres": [],
    "specification": {
      "minimum": "",
      "recommended": ""
    }
  },
  {
    "appid": 365580,
    "title": "Beeswing",
    "premium": false,
    "cover_url": "NO CONTENT",
    "publishers": [],
    "genres": [],
    "specification": {
      "minimum": "",
      "recommended": ""
    }
  },
  {
    "appid": 365620,
    "title": "WarBirds 2026",
    "premium": true,
    "cover_url": "https://shared.steamstatic.com/store_item_assets/steam/apps/365620/03f6b17fe43888e0af7d8850f03b8c2e62665817/library_capsule.jpg?t=1762809948",
    "publishers": [],
    "genres": [],
    "specification": {
      "minimum": "",
      "recommended": ""
    }
  },
  {
    "appid": 365660,
    "title": "OlliOlli2: Welcome to Olliwood",
    "premium": true,
    "cover_url": "https://shared.steamstatic.com/store_item_assets/steam/apps/365660/library_600x900.jpg?t=1568670139",
    "publishers": [],
    "genres": [],
    "specification": {
      "minimum": "",
      "recommended": ""
    }
  },
  {
    "appid": 365680,
    "title": "BRAWL",
    "premium": true,
    "cover_url": "NO CONTENT",
    "publishers": [],
    "genres": [],
    "specification": {
      "minimum": "",
      "recommended": ""
    }
  },
  {
    "appid": 365730,
    "title": "Gilbert Goodmate and the Mushroom of Phungoria",
    "premium": false,
    "cover_url": "NO CONTENT",
    "publishers": [],
    "genres": [],
    "specification": {
      "minimum": "",
      "recommended": ""
    }
  },
  {
    "appid": 365760,
    "title": "Vektor Wars",
    "premium": false,
    "cover_url": "NO CONTENT",
    "publishers": [],
    "genres": [],
    "specification": {
      "minimum": "",
      "recommended": ""
    }
  },
  {
    "appid": 365770,
    "title": "Volume",
    "premium": true,
    "cover_url": "https://shared.steamstatic.com/store_item_assets/steam/apps/365770/library_600x900.jpg?t=1571520982",
    "publishers": [],
    "genres": [],
    "specification": {
      "minimum": "",
      "recommended": ""
    }
  },
  {
    "appid": 365800,
    "title": "AdvertCity",
    "premium": false,
    "cover_url": "NO CONTENT",
    "publishers": [],
    "genres": [],
    "specification": {
      "minimum": "",
      "recommended": ""
    }
  },
  {
    "appid": 365810,
    "title": "Flying Tigers: Shadows Over China",
    "premium": false,
    "cover_url": "NO CONTENT",
    "publishers": [],
    "genres": [],
    "specification": {
      "minimum": "",
      "recommended": ""
    }
  },
  {
    "appid": 365820,
    "title": "Company of Heroes 2 - The British Forces",
    "premium": true,
    "cover_url": "NO CONTENT",
    "publishers": [],
    "genres": [],
    "specification": {
      "minimum": "",
      "recommended": ""
    }
  },
  {
    "appid": 365850,
    "title": "Starchaser: Priestess of the Night Sky",
    "premium": false,
    "cover_url": "https://shared.steamstatic.com/store_item_assets/steam/apps/365850/library_600x900.jpg?t=1572922419",
    "publishers": [],
    "genres": [],
    "specification": {
      "minimum": "",
      "recommended": ""
    }
  },
  {
    "appid": 365860,
    "title": "Spaceman Sparkles 2",
    "premium": false,
    "cover_url": "NO CONTENT",
    "publishers": [],
    "genres": [],
    "specification": {
      "minimum": "",
      "recommended": ""
    }
  },
  {
    "appid": 365870,
    "title": "Below Kryll",
    "premium": false,
    "cover_url": "NO CONTENT",
    "publishers": [
      "Team Kryll"
    ],
    "genres": [
      "Action",
      "Adventure",
      "Indie",
      "RPG"
    ],
    "specification": {
      "minimum": "<strong>Minimum:</strong><br><ul class=\"bb_ul\"><li><strong>OS *:</strong> Windows XP<br></li><li><strong>Memory:</strong> 1 GB RAM<br></li><li><strong>Network:</strong> Broadband Internet connection<br></li><li><strong>Storage:</strong> 100 MB available space</li></ul>",
      "recommended": "<strong>Recommended:</strong><br><ul class=\"bb_ul\"><li><strong>OS *:</strong> Windows 7<br></li><li><strong>Memory:</strong> 1 GB RAM<br></li><li><strong>Network:</strong> Broadband Internet connection<br></li><li><strong>Storage:</strong> 100 MB available space</li></ul>"
    }
  },
  {
    "appid": 365880,
    "title": "Mirrored - Chapter 1",
    "premium": false,
    "cover_url": "NO CONTENT",
    "publishers": [],
    "genres": [],
    "specification": {
      "minimum": "",
      "recommended": ""
    }
  },
  {
    "appid": 365890,
    "title": "Heroes of Normandie",
    "premium": true,
    "cover_url": "https://shared.steamstatic.com/store_item_assets/steam/apps/365890/library_600x900.jpg?t=1623938777",
    "publishers": [],
    "genres": [],
    "specification": {
      "minimum": "",
      "recommended": ""
    }
  },
  {
    "appid": 365900,
    "title": "Pixel Dungeon",
    "premium": false,
    "cover_url": "NO CONTENT",
    "publishers": [],
    "genres": [],
    "specification": {
      "minimum": "",
      "recommended": ""
    }
  },
  {
    "appid": 365960,
    "title": "rFactor 2",
    "premium": true,
    "cover_url": "https://shared.steamstatic.com/store_item_assets/steam/apps/365960/library_600x900.jpg?t=1700569634",
    "publishers": [],
    "genres": [],
    "specification": {
      "minimum": "",
      "recommended": ""
    }
  },
  {
    "appid": 366000,
    "title": "Rogue System",
    "premium": false,
    "cover_url": "NO CONTENT",
    "publishers": [],
    "genres": [],
    "specification": {
      "minimum": "",
      "recommended": ""
    }
  },
  {
    "appid": 366010,
    "title": "Generic Space Shooter",
    "premium": false,
    "cover_url": "https://shared.steamstatic.com/store_item_assets/steam/apps/366010/library_600x900.jpg?t=1691284364",
    "publishers": [],
    "genres": [],
    "specification": {
      "minimum": "",
      "recommended": ""
    }
  },
  {
    "appid": 366050,
    "title": "Star Balls",
    "premium": false,
    "cover_url": "NO CONTENT",
    "publishers": [],
    "genres": [],
    "specification": {
      "minimum": "",
      "recommended": ""
    }
  },
  {
    "appid": 366060,
    "title": "Teddy Terror",
    "premium": false,
    "cover_url": "NO CONTENT",
    "publishers": [],
    "genres": [],
    "specification": {
      "minimum": "",
      "recommended": ""
    }
  },
  {
    "appid": 366090,
    "title": "Colony Survival",
    "premium": true,
    "cover_url": "https://shared.steamstatic.com/store_item_assets/steam/apps/366090/library_600x900.jpg?t=1719315232",
    "publishers": [],
    "genres": [],
    "specification": {
      "minimum": "",
      "recommended": ""
    }
  },
  {
    "appid": 366100,
    "title": "Champions Of Chaos 2",
    "premium": false,
    "cover_url": "NO CONTENT",
    "publishers": [],
    "genres": [],
    "specification": {
      "minimum": "",
      "recommended": ""
    }
  },
  {
    "appid": 366180,
    "title": "Disposable Heroes",
    "premium": false,
    "cover_url": "NO CONTENT",
    "publishers": [],
    "genres": [],
    "specification": {
      "minimum": "",
      "recommended": ""
    }
  },
  {
    "appid": 366210,
    "title": "Sleep Attack",
    "premium": false,
    "cover_url": "https://shared.steamstatic.com/store_item_assets/steam/apps/366210/library_600x900.jpg?t=1568807181",
    "publishers": [],
    "genres": [],
    "specification": {
      "minimum": "",
      "recommended": ""
    }
  },
  {
    "appid": 366220,
    "title": "Wurm Unlimited",
    "premium": true,
    "cover_url": "https://shared.steamstatic.com/store_item_assets/steam/apps/366220/library_600x900.jpg?t=1750428828",
    "publishers": [],
    "genres": [],
    "specification": {
      "minimum": "",
      "recommended": ""
    }
  },
  {
    "appid": 366230,
    "title": "BASEBALL STARS 2",
    "premium": false,
    "cover_url": "https://shared.steamstatic.com/store_item_assets/steam/apps/366230/library_600x900.jpg?t=1580723129",
    "publishers": [],
    "genres": [],
    "specification": {
      "minimum": "",
      "recommended": ""
    }
  },
  {
    "appid": 366240,
    "title": "GAROU: MARK OF THE WOLVES",
    "premium": false,
    "cover_url": "NO CONTENT",
    "publishers": [],
    "genres": [],
    "specification": {
      "minimum": "",
      "recommended": ""
    }
  },
  {
    "appid": 366250,
    "title": "METAL SLUG",
    "premium": false,
    "cover_url": "https://shared.steamstatic.com/store_item_assets/steam/apps/366250/library_600x900.jpg?t=1572596226",
    "publishers": [],
    "genres": [],
    "specification": {
      "minimum": "",
      "recommended": ""
    }
  },
  {
    "appid": 366260,
    "title": "METAL SLUG 2",
    "premium": false,
    "cover_url": "https://shared.steamstatic.com/store_item_assets/steam/apps/366260/library_600x900.jpg?t=1572597303",
    "publishers": [],
    "genres": [],
    "specification": {
      "minimum": "",
      "recommended": ""
    }
  },
  {
    "appid": 366270,
    "title": "SHOCK TROOPERS",
    "premium": false,
    "cover_url": "https://shared.steamstatic.com/store_item_assets/steam/apps/366270/library_600x900.jpg?t=1572598216",
    "publishers": [],
    "genres": [],
    "specification": {
      "minimum": "",
      "recommended": ""
    }
  },
  {
    "appid": 366280,
    "title": "TWINKLE STAR SPRITES",
    "premium": false,
    "cover_url": "NO CONTENT",
    "publishers": [],
    "genres": [],
    "specification": {
      "minimum": "",
      "recommended": ""
    }
  },
  {
    "appid": 366290,
    "title": "Carp Fishing Simulator",
    "premium": true,
    "cover_url": "https://shared.steamstatic.com/store_item_assets/steam/apps/366290/library_600x900.jpg?t=1636794383",
    "publishers": [],
    "genres": [],
    "specification": {
      "minimum": "",
      "recommended": ""
    }
  },
  {
    "appid": 366320,
    "title": "Seasons after Fall",
    "premium": false,
    "cover_url": "https://shared.steamstatic.com/store_item_assets/steam/apps/366320/library_600x900.jpg?t=1666984484",
    "publishers": [],
    "genres": [],
    "specification": {
      "minimum": "",
      "recommended": ""
    }
  },
  {
    "appid": 366350,
    "title": "ROGUS - Kingdom of The Lost Souls",
    "premium": false,
    "cover_url": "NO CONTENT",
    "publishers": [],
    "genres": [],
    "specification": {
      "minimum": "",
      "recommended": ""
    }
  },
  {
    "appid": 366380,
    "title": "MYTH - Steam Edition",
    "premium": true,
    "cover_url": "NO CONTENT",
    "publishers": [],
    "genres": [],
    "specification": {
      "minimum": "",
      "recommended": ""
    }
  },
  {
    "appid": 366410,
    "title": "Ludoku",
    "premium": false,
    "cover_url": "NO CONTENT",
    "publishers": [],
    "genres": [],
    "specification": {
      "minimum": "",
      "recommended": ""
    }
  },
  {
    "appid": 366510,
    "title": "Ruzar - The Life Stone",
    "premium": false,
    "cover_url": "https://shared.steamstatic.com/store_item_assets/steam/apps/366510/library_600x900.jpg?t=1717416243",
    "publishers": [],
    "genres": [],
    "specification": {
      "minimum": "",
      "recommended": ""
    }
  },
  {
    "appid": 366570,
    "title": "CastleAbra",
    "premium": false,
    "cover_url": "NO CONTENT",
    "publishers": [],
    "genres": [],
    "specification": {
      "minimum": "",
      "recommended": ""
    }
  },
  {
    "appid": 366590,
    "title": "Prompt",
    "premium": false,
    "cover_url": "https://shared.steamstatic.com/store_item_assets/steam/apps/366590/library_600x900.jpg?t=1683486379",
    "publishers": [],
    "genres": [],
    "specification": {
      "minimum": "",
      "recommended": ""
    }
  },
  {
    "appid": 366610,
    "title": "Not without my donuts",
    "premium": false,
    "cover_url": "NO CONTENT",
    "publishers": [],
    "genres": [],
    "specification": {
      "minimum": "",
      "recommended": ""
    }
  },
  {
    "appid": 366620,
    "title": "Broken Bots",
    "premium": false,
    "cover_url": "NO CONTENT",
    "publishers": [],
    "genres": [],
    "specification": {
      "minimum": "",
      "recommended": ""
    }
  },
  {
    "appid": 366640,
    "title": "Shiness: The Lightning Kingdom",
    "premium": false,
    "cover_url": "https://shared.steamstatic.com/store_item_assets/steam/apps/366640/library_600x900.jpg?t=1563289492",
    "publishers": [],
    "genres": [],
    "specification": {
      "minimum": "",
      "recommended": ""
    }
  },
  {
    "appid": 366670,
    "title": "The Travels of Marco Polo",
    "premium": false,
    "cover_url": "https://shared.steamstatic.com/store_item_assets/steam/apps/366670/library_600x900.jpg?t=1750428962",
    "publishers": [],
    "genres": [],
    "specification": {
      "minimum": "",
      "recommended": ""
    }
  },
  {
    "appid": 366690,
    "title": "Cue Club 2: Pool & Snooker",
    "premium": true,
    "cover_url": "https://shared.steamstatic.com/store_item_assets/steam/apps/366690/97c7370e4c92b4044ac514435064611a79f383d5/library_600x900.jpg?t=1752859468",
    "publishers": [],
    "genres": [],
    "specification": {
      "minimum": "",
      "recommended": ""
    }
  },
  {
    "appid": 366700,
    "title": "Breakout Invaders",
    "premium": false,
    "cover_url": "NO CONTENT",
    "publishers": [],
    "genres": [],
    "specification": {
      "minimum": "",
      "recommended": ""
    }
  },
  {
    "appid": 366760,
    "title": "Adorables",
    "premium": true,
    "cover_url": "NO CONTENT",
    "publishers": [],
    "genres": [],
    "specification": {
      "minimum": "",
      "recommended": ""
    }
  },
  {
    "appid": 366780,
    "title": "Magical Eyes - Red is for Anguish",
    "premium": true,
    "cover_url": "https://shared.steamstatic.com/store_item_assets/steam/apps/366780/library_600x900.jpg?t=1667311170",
    "publishers": [],
    "genres": [],
    "specification": {
      "minimum": "",
      "recommended": ""
    }
  },
  {
    "appid": 366800,
    "title": "Mainland",
    "premium": false,
    "cover_url": "NO CONTENT",
    "publishers": [],
    "genres": [],
    "specification": {
      "minimum": "",
      "recommended": ""
    }
  },
  {
    "appid": 366870,
    "title": "Narcosis",
    "premium": false,
    "cover_url": "NO CONTENT",
    "publishers": [],
    "genres": [],
    "specification": {
      "minimum": "",
      "recommended": ""
    }
  },
  {
    "appid": 366910,
    "title": "The Long Journey Home",
    "premium": false,
    "cover_url": "https://shared.steamstatic.com/store_item_assets/steam/apps/366910/library_600x900.jpg?t=1579271898",
    "publishers": [],
    "genres": [],
    "specification": {
      "minimum": "",
      "recommended": ""
    }
  },
  {
    "appid": 366920,
    "title": "Ruler by Default",
    "premium": false,
    "cover_url": "NO CONTENT",
    "publishers": [],
    "genres": [],
    "specification": {
      "minimum": "",
      "recommended": ""
    }
  },
  {
    "appid": 366960,
    "title": "SECTOR",
    "premium": false,
    "cover_url": "NO CONTENT",
    "publishers": [],
    "genres": [],
    "specification": {
      "minimum": "",
      "recommended": ""
    }
  },
  {
    "appid": 366970,
    "title": "Mighty Switch Force! Hyper Drive Edition",
    "premium": false,
    "cover_url": "https://shared.steamstatic.com/store_item_assets/steam/apps/366970/library_600x900.jpg?t=1573151774",
    "publishers": [],
    "genres": [],
    "specification": {
      "minimum": "",
      "recommended": ""
    }
  },
  {
    "appid": 366990,
    "title": "Puzzle Station 15th Anniversary Retro Release",
    "premium": false,
    "cover_url": "NO CONTENT",
    "publishers": [],
    "genres": [],
    "specification": {
      "minimum": "",
      "recommended": ""
    }
  },
  {
    "appid": 367000,
    "title": "Fine Sweeper",
    "premium": false,
    "cover_url": "https://shared.steamstatic.com/store_item_assets/steam/apps/367000/library_600x900.jpg?t=1754340399",
    "publishers": [],
    "genres": [],
    "specification": {
      "minimum": "",
      "recommended": ""
    }
  },
  {
    "appid": 367010,
    "title": "Vernon's Legacy",
    "premium": false,
    "cover_url": "NO CONTENT",
    "publishers": [],
    "genres": [],
    "specification": {
      "minimum": "",
      "recommended": ""
    }
  },
  {
    "appid": 367030,
    "title": "Lootfest",
    "premium": false,
    "cover_url": "NO CONTENT",
    "publishers": [],
    "genres": [],
    "specification": {
      "minimum": "",
      "recommended": ""
    }
  },
  {
    "appid": 367040,
    "title": "InsanZ - Retro Survival Horror",
    "premium": false,
    "cover_url": "NO CONTENT",
    "publishers": [],
    "genres": [],
    "specification": {
      "minimum": "",
      "recommended": ""
    }
  },
  {
    "appid": 367050,
    "title": "Vindicator: Uprising",
    "premium": false,
    "cover_url": "NO CONTENT",
    "publishers": [],
    "genres": [],
    "specification": {
      "minimum": "",
      "recommended": ""
    }
  },
  {
    "appid": 367060,
    "title": "Helena The 3rd",
    "premium": false,
    "cover_url": "NO CONTENT",
    "publishers": [],
    "genres": [],
    "specification": {
      "minimum": "",
      "recommended": ""
    }
  },
  {
    "appid": 367080,
    "title": "Songbringer",
    "premium": true,
    "cover_url": "https://shared.steamstatic.com/store_item_assets/steam/apps/367080/library_600x900.jpg?t=1651438346",
    "publishers": [],
    "genres": [],
    "specification": {
      "minimum": "",
      "recommended": ""
    }
  },
  {
    "appid": 367110,
    "title": "Dustbowl",
    "premium": false,
    "cover_url": "NO CONTENT",
    "publishers": [],
    "genres": [],
    "specification": {
      "minimum": "",
      "recommended": ""
    }
  },
  {
    "appid": 367120,
    "title": "Seduce Me the Otome",
    "premium": false,
    "cover_url": "NO CONTENT",
    "publishers": [],
    "genres": [],
    "specification": {
      "minimum": "",
      "recommended": ""
    }
  },
  {
    "appid": 367140,
    "title": "Wish Project",
    "premium": false,
    "cover_url": "https://shared.steamstatic.com/store_item_assets/steam/apps/367140/library_600x900.jpg?t=1749774504",
    "publishers": [],
    "genres": [],
    "specification": {
      "minimum": "",
      "recommended": ""
    }
  },
  {
    "appid": 367220,
    "title": "Egyptian Settlement Gold",
    "premium": false,
    "cover_url": "NO CONTENT",
    "publishers": [],
    "genres": [],
    "specification": {
      "minimum": "",
      "recommended": ""
    }
  },
  {
    "appid": 367240,
    "title": "Avenging Angel",
    "premium": true,
    "cover_url": "NO CONTENT",
    "publishers": [],
    "genres": [],
    "specification": {
      "minimum": "",
      "recommended": ""
    }
  },
  {
    "appid": 367260,
    "title": "Dwarven Brawl Bros",
    "premium": false,
    "cover_url": "NO CONTENT",
    "publishers": [],
    "genres": [],
    "specification": {
      "minimum": "",
      "recommended": ""
    }
  },
  {
    "appid": 367270,
    "title": "Angels Fall First",
    "premium": true,
    "cover_url": "https://shared.steamstatic.com/store_item_assets/steam/apps/367270/library_600x900.jpg?t=1742339761",
    "publishers": [],
    "genres": [],
    "specification": {
      "minimum": "",
      "recommended": ""
    }
  },
  {
    "appid": 367300,
    "title": "Pixel Star",
    "premium": false,
    "cover_url": "https://shared.steamstatic.com/store_item_assets/steam/apps/367300/library_600x900.jpg?t=1671601341",
    "publishers": [],
    "genres": [],
    "specification": {
      "minimum": "",
      "recommended": ""
    }
  },
  {
    "appid": 367340,
    "title": "FleetCOMM",
    "premium": false,
    "cover_url": "NO CONTENT",
    "publishers": [],
    "genres": [],
    "specification": {
      "minimum": "",
      "recommended": ""
    }
  },
  {
    "appid": 367350,
    "title": "Demon Hearts",
    "premium": false,
    "cover_url": "NO CONTENT",
    "publishers": [],
    "genres": [],
    "specification": {
      "minimum": "",
      "recommended": ""
    }
  },
  {
    "appid": 367430,
    "title": "One Ship Two Ship Redshift Blueshift",
    "premium": false,
    "cover_url": "NO CONTENT",
    "publishers": [],
    "genres": [],
    "specification": {
      "minimum": "",
      "recommended": ""
    }
  },
  {
    "appid": 367450,
    "title": "Poly Bridge",
    "premium": false,
    "cover_url": "https://shared.steamstatic.com/store_item_assets/steam/apps/367450/library_600x900.jpg?t=1751450390",
    "publishers": [],
    "genres": [],
    "specification": {
      "minimum": "",
      "recommended": ""
    }
  },
  {
    "appid": 367500,
    "title": "Dragon's Dogma: Dark Arisen",
    "premium": true,
    "cover_url": "https://shared.steamstatic.com/store_item_assets/steam/apps/367500/library_600x900.jpg?t=1590390860",
    "publishers": [],
    "genres": [],
    "specification": {
      "minimum": "",
      "recommended": ""
    }
  },
  {
    "appid": 367520,
    "title": "Hollow Knight",
    "premium": true,
    "cover_url": "https://shared.steamstatic.com/store_item_assets/steam/apps/367520/library_600x900.jpg?t=1695270300",
    "publishers": [],
    "genres": [],
    "specification": {
      "minimum": "",
      "recommended": ""
    }
  },
  {
    "appid": 367550,
    "title": "Rugby League Team Manager 2015",
    "premium": true,
    "cover_url": "NO CONTENT",
    "publishers": [],
    "genres": [],
    "specification": {
      "minimum": "",
      "recommended": ""
    }
  },
  {
    "appid": 367570,
    "title": "oO",
    "premium": false,
    "cover_url": "https://shared.steamstatic.com/store_item_assets/steam/apps/367570/library_600x900.jpg?t=1667896966",
    "publishers": [],
    "genres": [],
    "specification": {
      "minimum": "",
      "recommended": ""
    }
  },
  {
    "appid": 367580,
    "title": "Hook",
    "premium": false,
    "cover_url": "https://shared.steamstatic.com/store_item_assets/steam/apps/367580/library_600x900.jpg?t=1653638332",
    "publishers": [],
    "genres": [],
    "specification": {
      "minimum": "",
      "recommended": ""
    }
  },
  {
    "appid": 367660,
    "title": "UfoPilot : Astro-Creeps Elite",
    "premium": false,
    "cover_url": "NO CONTENT",
    "publishers": [],
    "genres": [],
    "specification": {
      "minimum": "",
      "recommended": ""
    }
  },
  {
    "appid": 367700,
    "title": "SHOFER Race Driver",
    "premium": false,
    "cover_url": "NO CONTENT",
    "publishers": [],
    "genres": [],
    "specification": {
      "minimum": "",
      "recommended": ""
    }
  },
  {
    "appid": 367710,
    "title": "Afterlife Empire",
    "premium": false,
    "cover_url": "NO CONTENT",
    "publishers": [],
    "genres": [],
    "specification": {
      "minimum": "",
      "recommended": ""
    }
  },
  {
    "appid": 367780,
    "title": "Aero's Quest",
    "premium": false,
    "cover_url": "NO CONTENT",
    "publishers": [],
    "genres": [],
    "specification": {
      "minimum": "",
      "recommended": ""
    }
  },
  {
    "appid": 367800,
    "title": "Diamond Deeps",
    "premium": false,
    "cover_url": "NO CONTENT",
    "publishers": [],
    "genres": [],
    "specification": {
      "minimum": "",
      "recommended": ""
    }
  },
  {
    "appid": 367820,
    "title": "Decromancer",
    "premium": false,
    "cover_url": "NO CONTENT",
    "publishers": [],
    "genres": [],
    "specification": {
      "minimum": "",
      "recommended": ""
    }
  },
  {
    "appid": 367990,
    "title": "3D Paraglider",
    "premium": false,
    "cover_url": "NO CONTENT",
    "publishers": [],
    "genres": [],
    "specification": {
      "minimum": "",
      "recommended": ""
    }
  },
  {
    "appid": 368000,
    "title": "100ft Robot Golf",
    "premium": false,
    "cover_url": "https://shared.steamstatic.com/store_item_assets/steam/apps/368000/ca18a679a3d7a3218649783478d8e3728617834a/library_600x900.jpg?t=1729714646",
    "publishers": [],
    "genres": [],
    "specification": {
      "minimum": "",
      "recommended": ""
    }
  },
  {
    "appid": 368040,
    "title": "ExoCorps",
    "premium": true,
    "cover_url": "https://shared.steamstatic.com/store_item_assets/steam/apps/368040/library_600x900.jpg?t=1613866683",
    "publishers": [],
    "genres": [],
    "specification": {
      "minimum": "",
      "recommended": ""
    }
  },
  {
    "appid": 368050,
    "title": "Almightree: The Last Dreamer",
    "premium": false,
    "cover_url": "NO CONTENT",
    "publishers": [],
    "genres": [],
    "specification": {
      "minimum": "",
      "recommended": ""
    }
  },
  {
    "appid": 368080,
    "title": "Aurion: Legacy of the Kori-Odan",
    "premium": false,
    "cover_url": "https://shared.steamstatic.com/store_item_assets/steam/apps/368080/0618badbe24259d341ef0fe78a3e9e528bcb281f/library_600x900.jpg?t=1743173782",
    "publishers": [],
    "genres": [],
    "specification": {
      "minimum": "",
      "recommended": ""
    }
  },
  {
    "appid": 368140,
    "title": "Tobari and the Night of the Curious Moon",
    "premium": false,
    "cover_url": "https://shared.steamstatic.com/store_item_assets/steam/apps/368140/library_600x900.jpg?t=1595527495",
    "publishers": [],
    "genres": [],
    "specification": {
      "minimum": "",
      "recommended": ""
    }
  },
  {
    "appid": 368150,
    "title": "Rising Angels: Hope",
    "premium": true,
    "cover_url": "https://shared.steamstatic.com/store_item_assets/steam/apps/368150/library_600x900.jpg?t=1582671559",
    "publishers": [],
    "genres": [],
    "specification": {
      "minimum": "",
      "recommended": ""
    }
  }
]